{
  "version": "1.0",
  "file_id": "shinsal_psychology_db",
  "description": "주요 신살(神煞)을 인간의 심리·행동·관계 패턴으로 번역한 DB. shinsal_ext_rules.json의 상수·운세 정보와 분리된 '심리 언어' 레이어.",
  "usage_note": "shinsalDetector.py가 탐지한 신살 코드를 키로 이 DB를 참조해 감정·패턴 슬롯을 주입한다. shinsal_explanations.json은 상황별 운세 문장, 이 파일은 성향·반복 패턴 해석용.",
  "philosophy": "신살은 특정 성질의 에너지가 사주에 내재된 구조다. 좋고 나쁨이 아니라 그 사람이 반복적으로 경험하는 특정 패턴을 보여주는 신호로 읽는다.",
  "schema": {
    "shinsal_id": "신살 식별자 (shinsal_ext_rules.json 키 기준)",
    "label_ko": "한국어 이름",
    "category": "길신(guishin) / 흉살(hyungsal) / 중성(neutral)",
    "core_theme": "이 신살의 핵심 에너지 한 줄 정의",
    "psychological_profile": {
      "dominant_trait": "가장 두드러지는 심리적 특성",
      "behavior_pattern": "반복되는 행동 패턴 (3개)",
      "inner_state": "내면 상태 묘사 (3개)",
      "stress_response": "스트레스 상황에서 나타나는 반응 패턴"
    },
    "relation_pattern": "관계에서 반복되는 패턴 (3개)",
    "strength_context": "이 신살의 에너지가 실제 강점이 되는 상황 (2개)",
    "friction_context": "마찰이 생기기 쉬운 상황 (2개)",
    "reframe": "이 에너지를 다르게 읽는 시각 (2개)",
    "caution": "주의 포인트 1줄"
  },

  "shinsal_patterns": {

    "역마살": {
      "shinsal_id": "역마살",
      "label_ko": "역마살",
      "category": "neutral",
      "core_theme": "이동과 변화를 통해 에너지를 얻는 구조. 정착보다 움직임에서 자신이 살아있음을 느낀다.",
      "psychological_profile": {
        "dominant_trait": "변화 지향성과 이동 본능. 같은 자리에 오래 머무는 것을 본능적으로 불편해한다.",
        "behavior_pattern": [
          "환경, 직장, 관계에서 변화를 자주 만들어내며, 때로는 안정된 상황에서도 이동을 선택한다.",
          "새로운 곳, 새로운 사람, 새로운 상황에 에너지가 올라오고, 익숙해질수록 활력이 줄어드는 경향이 있다.",
          "계획보다 즉흥적인 결정이 더 잘 맞는 경우가 많으며, 현장에서의 판단이 빠르다."
        ],
        "inner_state": [
          "정체된 상황이 오래되면 내부에서 답답함과 불안이 올라온다.",
          "이동하고 있을 때, 새로운 것을 만나고 있을 때 가장 살아있다는 느낌이 든다.",
          "정착해야 한다는 사회적 기대와 이동하고 싶은 내부 욕구 사이에서 갈등을 느끼는 경우가 있다."
        ],
        "stress_response": "스트레스 상황에서 환경을 바꾸는 것으로 해결하려는 경향이 있다. 문제를 직접 해결하기보다 자리를 옮기는 방식이 먼저 나올 수 있다."
      },
      "relation_pattern": [
        "관계에서도 새로운 만남에 에너지가 높고, 오래된 관계가 익숙해지면 거리감이 생기기 쉽다.",
        "파트너가 안정을 원하고 자신이 변화를 원할 때 지속적인 긴장이 생긴다.",
        "이동이나 변화를 함께 즐길 수 있는 사람과 가장 잘 맞는 관계가 형성된다."
      ],
      "strength_context": [
        "새로운 시장, 새로운 환경, 해외, 이동이 많은 업종에서 실제 강점이 드러난다.",
        "여러 환경을 경험해 적응력과 현장 감각이 뛰어난 역할에서 두각을 나타낸다."
      ],
      "friction_context": [
        "같은 자리에서 오래 집중해야 하는 업무나 장기 루틴이 요구될 때",
        "파트너나 가족이 안정과 정착을 강하게 원할 때"
      ],
      "reframe": [
        "이동 본능이 강한 것은 변화 속에서 기회를 먼저 찾는 능력이기도 하다.",
        "익숙함에 안주하지 않는 것은 성장 지향성의 다른 이름이다."
      ],
      "caution": "이동과 변화 자체가 목적이 되지 않도록, 지금 있는 곳에서 얻을 수 있는 것을 먼저 확인하는 습관이 도움이 된다."
    },

    "도화살": {
      "shinsal_id": "도화살",
      "label_ko": "도화살",
      "category": "neutral",
      "core_theme": "매력과 감수성이 외부로 자연스럽게 발산되는 구조. 사람을 끌어당기는 에너지가 있다.",
      "psychological_profile": {
        "dominant_trait": "대인 감수성과 표현 욕구. 타인의 시선과 반응에 자연스럽게 안테나가 켜져 있다.",
        "behavior_pattern": [
          "사람들과의 교류에서 에너지를 얻으며, 사회적 상황에서 자연스럽게 주목을 받는 경우가 많다.",
          "자신을 표현하는 것에 거부감이 없으며, 외모나 분위기에 신경을 쓰는 것이 자연스럽다.",
          "상대의 기분과 반응을 빠르게 읽으며, 그에 맞춰 반응하는 능력이 있다."
        ],
        "inner_state": [
          "인정과 관심을 받을 때 내면 에너지가 올라오며, 주목받지 못할 때 공허함이 온다.",
          "혼자 있어도 상대방의 시선이나 반응을 의식하는 내부 안테나가 쉽게 꺼지지 않는다.",
          "자신의 매력이 상대에게 제대로 전달되고 있는지 체크하는 내부 감각이 있다."
        ],
        "stress_response": "스트레스 상황에서 관계나 사람에게 집중하거나, 반대로 과도하게 고립되는 방향으로 나뉜다."
      },
      "relation_pattern": [
        "관계 형성이 빠르고 호감을 사는 능력이 있지만, 여러 관계가 동시에 얽히는 복잡한 상황이 생기기도 한다.",
        "상대에게 호감을 주는 것이 자연스럽지만, 그것이 때로 의도와 다르게 읽히는 경우가 있다.",
        "깊이 있는 관계보다 다양한 관계를 선호하는 경향이 있으며, 하나의 관계에 몰입하는 것이 어렵게 느껴질 때가 있다."
      ],
      "strength_context": [
        "대인 서비스, 표현이 필요한 창작, 영업, 상담 등 사람을 만나는 일에서 강점이 발현된다.",
        "다양한 사람을 만나고 연결하는 역할에서 자연스러운 에너지가 나온다."
      ],
      "friction_context": [
        "한 사람이나 한 관계에 집중해야 하는 상황에서 방산이 생길 수 있다.",
        "자신의 의도와 다르게 관계가 복잡해지는 상황이 반복될 수 있다."
      ],
      "reframe": [
        "매력은 통제하는 것이 아니라 방향을 정하는 것이다. 그 에너지를 원하는 곳에 집중하면 강력한 도구가 된다.",
        "사람을 읽는 감각이 뛰어나다는 것은 관계에서 필요한 것을 빠르게 파악한다는 의미이기도 하다."
      ],
      "caution": "외부 관심에 동기가 크게 연결되어 있다면, 내부 기준을 하나 만들어두는 것이 장기적으로 안정감을 준다."
    },

    "괴강살": {
      "shinsal_id": "괴강살",
      "label_ko": "괴강살",
      "category": "neutral",
      "core_theme": "강한 독립성과 원칙 중심의 구조. 흔들리지 않는 중심이 있지만 그만큼 충돌도 잦다.",
      "psychological_profile": {
        "dominant_trait": "강한 자기 중심성과 원칙 고수. 타협이 어렵고, 자신의 판단을 신뢰하는 경향이 강하다.",
        "behavior_pattern": [
          "일이든 관계든 자신의 방식과 기준을 중심으로 정렬하려는 경향이 있다.",
          "강하게 밀어붙이는 힘이 있으며, 어려운 상황에서도 쉽게 포기하지 않는다.",
          "부당하다고 느끼는 것에 강하게 반응하며, 불합리한 상황을 참고 넘기는 것을 어려워한다."
        ],
        "inner_state": [
          "자신의 판단이 옳다는 확신이 강하며, 외부의 의견이 그것과 다를 때 불편함이 크다.",
          "강인함을 유지하는 것 자체에 에너지를 쓰는 구조여서, 내면에서 피로가 쌓이는 경우가 있다.",
          "혼자서 처리하는 것이 편하며, 타인에게 기대는 것을 내키지 않아 하는 경향이 있다."
        ],
        "stress_response": "스트레스 상황에서 더 강하게 밀어붙이거나, 모든 것을 혼자 처리하려는 패턴이 나온다. 도움을 요청하는 것이 취약함을 드러내는 것처럼 느껴질 수 있다."
      },
      "relation_pattern": [
        "관계에서 자신의 방식을 중심으로 정렬하려는 경향이 있어, 주도권 충돌이 생기기 쉽다.",
        "강한 성향의 파트너와 강하게 연결되기도 하지만, 충돌도 크다.",
        "신뢰가 한번 깨지면 회복이 어렵고, 다시 여는 데 상당한 시간이 걸린다."
      ],
      "strength_context": [
        "어려운 상황을 혼자 극복해야 할 때, 강한 추진력과 독립성이 실제 강점이 된다.",
        "원칙과 기준이 중요한 환경에서, 타협하지 않는 일관성이 신뢰로 이어진다."
      ],
      "friction_context": [
        "협력과 유연성이 요구되는 팀 환경에서 독자 행동이 마찰을 만들 수 있다.",
        "자신의 강한 에너지가 상대에게 위압감을 주는 것을 인식하지 못하는 상황"
      ],
      "reframe": [
        "강한 원칙은 흔들리지 않는 신뢰의 기반이 된다. 그 중심이 올바른 방향을 향하고 있을 때 주변에 안정감을 준다.",
        "혼자 강하게 버티는 힘은 주변이 무너질 때 가장 빛난다."
      ],
      "caution": "강함이 벽이 되지 않도록, 한 번씩 '내가 놓치고 있는 것이 있는가'를 열린 자세로 점검하는 루틴이 필요하다."
    },

    "귀문관살": {
      "shinsal_id": "귀문관살",
      "label_ko": "귀문관살",
      "category": "neutral",
      "core_theme": "감각이 보통보다 얇고 예민한 구조. 일반적인 채널 이외의 것을 포착하는 능력이 있다.",
      "psychological_profile": {
        "dominant_trait": "고도의 감수성과 직관력. 타인이 포착하지 못하는 것을 먼저 감지하지만, 그로 인해 소모가 크다.",
        "behavior_pattern": [
          "분위기, 사람의 감정, 공간의 에너지에 예민하게 반응하며, 그것이 의식하지 않아도 자동으로 작동한다.",
          "혼자만의 시간이 필요하며, 많은 자극이 동시에 오면 회복에 시간이 걸린다.",
          "직관적인 판단이 분석보다 먼저 오는 경우가 많으며, 그 직관이 나중에 맞는 것으로 드러나는 경험이 반복된다."
        ],
        "inner_state": [
          "세상이 때로는 지나치게 선명하게 느껴지며, 그 선명함이 때로는 피로가 된다.",
          "말로 설명하기 어려운 감각적 인식이 자주 있으며, 그것을 정확히 표현하는 데 어려움을 느낀다.",
          "자신의 예민함이 결함이 아닐까 의심하거나, 그것을 숨기려는 경향이 있을 수 있다."
        ],
        "stress_response": "과자극 상황에서 완전한 고립을 원하거나, 감각을 차단하려는 방향으로 반응한다. 극도의 피로가 올 때 기능이 급격히 저하될 수 있다."
      },
      "relation_pattern": [
        "상대의 감정 상태를 말보다 먼저 읽으며, 이것이 공감 능력으로 이어지지만 상대의 감정을 자신의 것처럼 받아들이는 소모가 생기기도 한다.",
        "깊은 연결을 원하지만 그 연결이 너무 강해지면 오히려 거리를 두는 패턴이 있다.",
        "관계에서 말하지 않아도 알아주기를 바라는 경향이 있어, 그것이 전달되지 않을 때 고립감이 온다."
      ],
      "strength_context": [
        "상담, 창작, 심리, 예술처럼 감각적 포착이 핵심인 분야에서 남다른 능력이 나온다.",
        "다른 사람이 놓치는 신호를 먼저 감지해야 하는 상황에서 실질적 강점이 된다."
      ],
      "friction_context": [
        "자극이 많고 소음이 많은 환경에서 집중력과 에너지가 빠르게 소진된다.",
        "자신의 감각이 과도하게 작동해 실제보다 상황을 크게 읽는 경우가 생길 수 있다."
      ],
      "reframe": [
        "예민함은 더 많은 정보를 수집하는 능력이다. 그것이 피로가 되지 않도록 관리하는 것이 핵심이다.",
        "직관이 강한 사람은 분석으로 접근하는 사람이 놓치는 것을 먼저 본다."
      ],
      "caution": "예민함을 무감각으로 덮으려 하기보다, 자극을 조절하는 환경을 의식적으로 만드는 것이 지속 가능한 방법이다."
    },

    "홍염살": {
      "shinsal_id": "홍염살",
      "label_ko": "홍염살",
      "category": "neutral",
      "core_theme": "내면의 열기와 감정 강도가 높은 구조. 몰입과 열정이 강하지만, 그 에너지가 감정의 진폭도 크게 만든다.",
      "psychological_profile": {
        "dominant_trait": "감정 강도와 몰입력. 관심 있는 것에는 깊이 빠져들고, 그렇지 않은 것에는 에너지가 전혀 가지 않는다.",
        "behavior_pattern": [
          "한번 빠지면 깊이 몰입하는 경향이 있으며, 그것이 일이든 관계든 마찬가지다.",
          "감정의 진폭이 커서 좋을 때와 힘들 때의 차이가 뚜렷하게 나타난다.",
          "열정이 있을 때는 강하게 밀어붙이지만, 그 열정이 식으면 급격히 에너지가 빠지는 패턴이 있다."
        ],
        "inner_state": [
          "무언가에 강하게 이끌리는 감각이 자주 오며, 그것을 무시하기가 어렵다.",
          "감정이 강하게 올라올 때 그것을 가라앉히는 데 시간이 걸리며, 그 상태에서의 판단이 나중에 후회로 이어지기도 한다.",
          "의미 있는 것에 몰입할 때 가장 살아있다는 감각이 강하게 온다."
        ],
        "stress_response": "스트레스 상황에서 감정이 먼저 올라오며, 냉정한 판단보다 즉각적인 반응이 먼저 나오는 경향이 있다."
      },
      "relation_pattern": [
        "관계에서도 강하게 몰입하는 구조여서, 상대에게 강한 인상을 주지만 그만큼 강도가 부담될 수 있다.",
        "감정적 연결이 강할 때는 깊이 연결되고, 그 연결이 식으면 관계 자체에 의구심이 생기는 패턴이 있다.",
        "파트너에게도 비슷한 수준의 열정과 몰입을 기대하며, 그것이 충족되지 않으면 실망이 크다."
      ],
      "strength_context": [
        "몰입이 필요한 창작, 연구, 전문 분야에서 남다른 깊이를 만들어낸다.",
        "열정이 전달되어야 하는 상황, 설득과 영감이 필요한 역할에서 강점이 나온다."
      ],
      "friction_context": [
        "감정이 과도하게 올라온 상태에서 중요한 결정이나 대화가 이루어질 때",
        "열정이 식은 후 의무감만으로 유지해야 하는 상황"
      ],
      "reframe": [
        "감정이 강하다는 것은 삶을 더 깊이 경험한다는 의미이기도 하다.",
        "몰입의 깊이가 깊은 사람은 그 분야에서 일반적인 수준을 넘어서는 결과를 만들어낸다."
      ],
      "caution": "감정이 올라온 상태에서의 결정은 24시간 후에 다시 확인하는 습관이 후회를 줄여준다."
    },

    "백호살": {
      "shinsal_id": "백호살",
      "label_ko": "백호살",
      "category": "neutral",
      "core_theme": "강렬하고 급격한 에너지의 구조. 돌파력이 강하지만 예측하기 어려운 방식으로 작동하는 경우가 있다.",
      "psychological_profile": {
        "dominant_trait": "강한 추진력과 긴박감. 상황을 빠르게 처리하려는 본능과 강렬한 반응 방식.",
        "behavior_pattern": [
          "위기 상황에서 빠르게 대응하는 능력이 있으며, 급박한 상황에서 오히려 명확해지는 경향이 있다.",
          "강한 자극에 강하게 반응하며, 평온한 상황보다 긴장감이 있는 환경에서 더 활성화된다.",
          "한번 결정하면 강하게 밀어붙이며, 중간에 방향을 바꾸는 것을 싫어한다."
        ],
        "inner_state": [
          "평온한 상태보다 약간의 긴장감이 있을 때 오히려 집중력이 높아지는 경험이 있다.",
          "강하게 살아있다는 감각이 있을 때 가장 자신답다고 느낀다.",
          "에너지가 과도할 때 내부에서 과부하 신호가 오는 것을 늦게 인식하는 경향이 있다."
        ],
        "stress_response": "스트레스 상황에서 더 강하고 빠르게 반응하는 경향이 있다. 한 발 물러서는 것보다 정면 돌파를 먼저 시도한다."
      },
      "relation_pattern": [
        "관계에서 강하게 연결되거나 강하게 갈등하는 방식으로 나타나며, 중간 지점이 흐릿한 경우가 있다.",
        "상대에게 강렬한 인상을 주지만, 그 강도가 상대를 압도하거나 부담을 줄 수 있다.",
        "갈등 상황에서 강하게 반응한 뒤 후회하거나, 그 이후 관계 회복에 어려움을 겪는 패턴이 있다."
      ],
      "strength_context": [
        "위기 상황에서의 빠른 대응, 강한 추진력이 필요한 단기 목표",
        "강인함과 결단력이 요구되는 역할, 도전적인 환경"
      ],
      "friction_context": [
        "세심하고 느린 조율이 필요한 협력 상황",
        "에너지가 과도하게 올라온 상태에서의 중요한 대화나 결정"
      ],
      "reframe": [
        "강한 에너지는 방향이 맞으면 큰 결과를 만들어낸다. 그 힘을 어디에 쓸지가 결과를 결정한다.",
        "위기에서 빠르게 기능하는 능력은 일상에서는 보이지 않지만 중요한 순간에 작동하는 자산이다."
      ],
      "caution": "반응 속도가 빠른 만큼, 중요한 결정 앞에서 의도적으로 한 박자 쉬는 연습이 필요하다."
    },

    "천을귀인": {
      "shinsal_id": "천을귀인",
      "label_ko": "천을귀인",
      "category": "guishin",
      "core_theme": "필요한 순간 도움이 연결되는 구조. 혼자 해결하는 것보다 관계와 협력 안에서 더 큰 힘이 나온다.",
      "psychological_profile": {
        "dominant_trait": "관계 자원을 자연스럽게 활용하는 능력. 적절한 시기에 필요한 사람이 나타나거나 연결이 이루어지는 경험이 반복된다.",
        "behavior_pattern": [
          "혼자 해결하는 것보다 관계를 통해 해결이 이루어지는 경험이 반복되며, 인적 자원이 실제 자원이 된다.",
          "위기 상황에서 예상치 못한 도움이 나타나거나, 막혔던 것이 풀리는 경험이 있다.",
          "자신도 타인에게 도움이 되는 역할을 자연스럽게 맡는 경향이 있다."
        ],
        "inner_state": [
          "혼자 모든 것을 해결해야 한다는 압박보다, 연결 안에서 길이 열린다는 감각이 있다.",
          "관계를 소중히 여기는 본능이 있으며, 그것이 장기적으로 자원이 된다는 것을 직관적으로 안다.",
          "도움을 받는 것에 편안함을 느끼면서도, 그것을 언제 구해야 하는지 감각이 있다."
        ],
        "stress_response": "스트레스 상황에서 주변의 도움을 자연스럽게 받아들이거나, 연결된 관계를 통해 돌파구를 찾는 방향으로 움직인다."
      },
      "relation_pattern": [
        "관계에서 신뢰를 중요하게 여기며, 그 신뢰가 나중에 실질적인 도움으로 돌아오는 경험이 반복된다.",
        "사람과의 연결을 소홀히 하지 않아, 오래된 관계가 나중에 뜻밖의 방식으로 작동하는 경우가 있다.",
        "도움을 주는 것과 받는 것이 자연스럽게 순환되는 관계를 형성한다."
      ],
      "strength_context": [
        "네트워크와 인적 자원이 중요한 분야, 협력과 연결이 결과를 만드는 상황",
        "위기 상황에서 관계 자원을 활용해야 할 때"
      ],
      "friction_context": [
        "완전히 혼자서 처리해야 하는 상황에서 관계 자원이 없을 때",
        "도움을 받는 것을 약함으로 여기는 환경에서"
      ],
      "reframe": [
        "혼자 해결하지 않는 것이 의존이 아니라 관계 자원을 현명하게 사용하는 능력이다.",
        "내가 도움을 받는 것만큼, 나도 누군가에게 그 도움이 되고 있다."
      ],
      "caution": "관계 자원이 있다는 것에 과도하게 의존하기보다, 자신의 실력도 함께 키우는 것이 균형을 만든다."
    },

    "문창귀인": {
      "shinsal_id": "문창귀인",
      "label_ko": "문창귀인",
      "category": "guishin",
      "core_theme": "지적 활동과 표현에서 에너지를 얻는 구조. 배우고 정리하고 전달하는 것이 자연스럽다.",
      "psychological_profile": {
        "dominant_trait": "지적 탐구 욕구와 정리·표현 능력. 아는 것을 체계화하고 전달하는 것에서 만족감이 크다.",
        "behavior_pattern": [
          "새로운 것을 배우는 것에 에너지가 올라오며, 알게 된 것을 정리하고 표현하는 것이 자연스럽다.",
          "글, 언어, 설명, 기록에 강점이 있으며, 복잡한 것을 명확하게 정리하는 능력이 있다.",
          "지적으로 자극이 없거나 배움이 멈춘 환경에서 에너지가 빠르게 떨어진다."
        ],
        "inner_state": [
          "무언가를 이해했을 때의 만족감이 크며, 그것이 주요 동기 원천이다.",
          "아직 모르는 것이 있다는 것이 불안보다 흥미로 먼저 읽힌다.",
          "내가 아는 것이 상대에게 전달되어 도움이 될 때 깊은 보람을 느낀다."
        ],
        "stress_response": "스트레스 상황에서 더 많이 알려고 하거나, 상황을 분석하고 정리하는 방향으로 대응하는 경향이 있다."
      },
      "relation_pattern": [
        "지적 자극이 되는 대화와 관계에서 깊은 연결을 느끼며, 배울 것이 없는 관계는 지루하게 느껴진다.",
        "상대에게 자신이 아는 것을 나누려는 욕구가 있으며, 그것이 때로는 가르치려는 것으로 읽힐 수 있다.",
        "생각과 이야기를 나눌 수 있는 사람과 가장 편안한 관계가 형성된다."
      ],
      "strength_context": [
        "학습, 연구, 글쓰기, 교육, 콘텐츠 분야에서 자연스러운 능력이 발현된다.",
        "복잡한 정보를 이해하고 정리해 전달해야 하는 상황"
      ],
      "friction_context": [
        "분석과 이해보다 빠른 실행이 요구되는 상황",
        "지식의 가치가 인정받지 못하는 환경"
      ],
      "reframe": [
        "배움의 욕구가 강한 것은 성장을 멈추지 않는 구조다.",
        "정리하고 전달하는 능력은 혼자 갖고 있는 것보다 나누었을 때 더 큰 가치가 된다."
      ],
      "caution": "아는 것을 나누는 것과 가르치는 것의 차이를 인식하면 관계에서의 마찰이 줄어든다."
    },

    "혈인살": {
      "shinsal_id": "혈인살",
      "label_ko": "혈인살",
      "category": "neutral",
      "core_theme": "날카롭고 빠른 처리 에너지. 절단하고 분리하는 힘이 강하지만, 그것이 관계나 상황에도 작동한다.",
      "psychological_profile": {
        "dominant_trait": "빠른 판단과 절단력. 불필요한 것을 빠르게 걷어내는 능력이 있지만, 그 기준이 관계에도 적용된다.",
        "behavior_pattern": [
          "애매한 상황을 정리하고 명확하게 구분 짓는 것이 자연스럽다.",
          "필요 없다고 판단하면 미련 없이 정리하는 경향이 있으며, 그 속도가 빠른 편이다.",
          "효율을 중요시하며, 비효율적인 과정이나 관계를 불편하게 여긴다."
        ],
        "inner_state": [
          "복잡하고 엉킨 상황보다 명확하게 정리된 상태에서 안정감을 느낀다.",
          "판단이 빠른 만큼, 때로는 너무 빨리 결론을 내렸다는 것을 나중에 인식하기도 한다.",
          "절단하고 정리하는 에너지가 강하지만, 그것이 자신의 내부에도 작동해 소모가 생기는 경우가 있다."
        ],
        "stress_response": "스트레스 상황에서 더 빠르게 정리하고 분리하려는 방향으로 반응한다. 관계나 상황을 끊어내는 것이 해결책으로 먼저 떠오를 수 있다."
      },
      "relation_pattern": [
        "관계에서도 명확한 기준과 경계를 중요시하며, 그 기준이 어긋나면 관계를 정리하는 것을 두려워하지 않는다.",
        "관계의 복잡함이나 모호함을 불편하게 여기며, 명확한 역할과 거리를 선호한다.",
        "한번 관계가 정리되면 다시 여는 것이 쉽지 않다."
      ],
      "strength_context": [
        "명확한 기준과 결단이 필요한 상황, 복잡한 것을 정리하고 구조화해야 할 때",
        "불필요한 것을 걷어내고 핵심에 집중해야 하는 국면"
      ],
      "friction_context": [
        "모호함과 유연성이 필요한 협력 상황",
        "상대의 속도에 맞춰 관계를 유지해야 할 때"
      ],
      "reframe": [
        "불필요한 것을 빠르게 정리하는 능력은 삶을 가볍게 유지하는 힘이다.",
        "명확한 경계를 만드는 것은 관계를 지속 가능하게 만드는 조건이기도 하다."
      ],
      "caution": "빠른 절단이 해결책처럼 느껴질 때, 한 번 더 '이것이 최선인가'를 확인하는 것이 나중의 후회를 줄인다."
    },

    "천라지망": {
      "shinsal_id": "천라지망",
      "label_ko": "천라지망",
      "category": "neutral",
      "core_theme": "걸리고 얽히는 구조. 빠져나가기 어려운 상황이 반복되지만, 그 안에서 깊이를 만들어가는 힘도 있다.",
      "psychological_profile": {
        "dominant_trait": "복잡한 상황에 깊이 연루되는 경향. 빠져나가려 할수록 더 얽히는 구조가 반복된다.",
        "behavior_pattern": [
          "책임이나 의무가 쌓이는 상황에서 벗어나기 어려우며, 거절하거나 끊어내는 것이 어렵게 느껴진다.",
          "상황이나 관계에서 오래 머무는 경향이 있으며, 떠나는 결정을 하기 전에 많이 고민한다.",
          "복잡한 상황을 정리하거나 탈출하는 시도를 하다가 오히려 더 깊이 연루되는 경험이 있다."
        ],
        "inner_state": [
          "이 상황에서 벗어나고 싶은 마음과 그것이 쉽지 않다는 현실이 공존한다.",
          "책임을 다하려는 마음이 강해서 끊어내는 것이 자신에게 불성실한 것처럼 느껴지기도 한다.",
          "얽힌 상황이 오래되면 무력감이 올라오는 경우가 있다."
        ],
        "stress_response": "스트레스 상황에서 벗어나려는 시도와 책임을 다하려는 양방향 힘이 동시에 작동해 소모가 크다."
      },
      "relation_pattern": [
        "관계에서 얽힌 상황, 복잡한 의무와 책임이 쌓이는 경험이 반복될 수 있다.",
        "관계를 끊거나 정리하는 것을 어려워하며, 그 결과 불편한 관계도 오래 유지하는 경향이 있다.",
        "관계에서의 책임감이 강해, 상대가 기대는 것을 거절하기 어렵다."
      ],
      "strength_context": [
        "복잡한 상황을 오래 견디며 처리해야 하는 역할, 책임감이 중요한 환경",
        "깊이 있게 관계하거나 상황에 몰두해야 하는 분야"
      ],
      "friction_context": [
        "빠르게 정리하고 다음으로 넘어가야 하는 환경",
        "여러 책임이 동시에 쌓여 처리 용량을 넘어설 때"
      ],
      "reframe": [
        "얽히는 것을 두려워하지 않는 힘이 복잡한 상황을 결국 해결하는 능력이 되기도 한다.",
        "깊이 연루되는 것은 그만큼 진심을 다한다는 의미이기도 하다."
      ],
      "caution": "책임감이 나를 소진시키고 있다면, '내 몫이 어디까지인가'를 한 문장으로 정의해두는 것이 도움이 된다."
    }
  },

  "combination_rules": {
    "_note": "여러 신살이 동시에 발현될 때 해석 가이드",
    "역마살+귀문관살": {
      "hint": "이동 본능과 예민한 감각이 동시에 있다. 새로운 환경에서 많은 것을 포착하는 능력이 있지만, 과자극으로 인한 소진도 빠를 수 있다. 이동 후 회복 간격을 충분히 두는 것이 필요하다."
    },
    "도화살+홍염살": {
      "hint": "매력과 감정 강도가 동시에 높다. 관계에서 강한 에너지를 주고받는 구조여서 깊은 연결이 이루어지지만, 그 강도 자체가 부담이 되거나 소모가 클 수 있다."
    },
    "괴강살+백호살": {
      "hint": "두 강한 에너지가 겹치는 구조다. 강한 추진력과 결단력이 배가되지만, 주변과의 마찰도 커질 수 있다. 그 힘이 올바른 방향을 향하고 있는지 주기적으로 점검하는 것이 핵심이다."
    },
    "천을귀인+문창귀인": {
      "hint": "관계 자원과 지적 능력이 동시에 있는 구조다. 사람과 지식을 연결하는 능력이 실질적인 강점이 되며, 교육·상담·컨텐츠 분야에서 특히 잘 작동한다."
    }
  },

  "engine_mapping": {
    "description": "shinsalDetector.py 출력 → 이 DB 키 매핑",
    "key_map": {
      "역마": "역마살",
      "도화": "도화살",
      "괴강": "괴강살",
      "귀문": "귀문관살",
      "홍염": "홍염살",
      "백호": "백호살",
      "천을귀인": "천을귀인",
      "문창귀인": "문창귀인",
      "혈인": "혈인살",
      "천라지망": "천라지망"
    },
    "slot_injection": {
      "dominant_trait": "리포트 도입 요약 슬롯 (1줄)",
      "behavior_pattern": "랜덤 1개, 'pattern' 슬롯",
      "inner_state": "랜덤 1개, 'emotion' 슬롯",
      "reframe": "랜덤 1개, 'insight' 슬롯",
      "caution": "'action' 슬롯 마지막 1줄",
      "relation_pattern": "궁합·관계 토픽 선택 시 우선 참조"
    }
  }
}
